csvdiff/__init__.py
csvdiff/error.py
csvdiff/patch.py
csvdiff/records.py
csvdiff-0.3.3.dist-info/DESCRIPTION.rst
csvdiff-0.3.3.dist-info/METADATA
csvdiff-0.3.3.dist-info/RECORD
csvdiff-0.3.3.dist-info/WHEEL
csvdiff-0.3.3.dist-info/entry_points.txt
csvdiff-0.3.3.dist-info/metadata.json
csvdiff-0.3.3.dist-info/top_level.txt
