Metadata-Version: 1.1
Name: csvdiff
Version: 0.3.3
Summary: Generate a diff between two CSV files.
Home-page: https://github.com/larsyencken/csvdiff
Author: Lars Yencken
Author-email: lars@yencken.org
License: BSD
Keywords: csvdiff
Platform: UNKNOWN
Classifier: Development Status :: 2 - Pre-Alpha
Classifier: Intended Audience :: Developers
Classifier: License :: OSI Approved :: BSD License
Classifier: Natural Language :: English
Classifier: Programming Language :: Python :: 2
Classifier: Programming Language :: Python :: 2.7
Classifier: Programming Language :: Python :: 3
Classifier: Programming Language :: Python :: 3.3
Classifier: Programming Language :: Python :: 3.4
